docs/conf.py
scripts/update_homebrew_formula.py
vss_cli/__init__.py
vss_cli/autocompletion.py
vss_cli/cli.py
vss_cli/config.py
vss_cli/const.py
vss_cli/data_types.py
vss_cli/exceptions.py
vss_cli/hcio.py
vss_cli/helper.py
vss_cli/ovf_helper.py
vss_cli/rel_opts.py
vss_cli/sstatus.py
vss_cli/validators.py
vss_cli/vss.py
vss_cli/vssconst.py
vss_cli/yaml.py
vss_cli/credentials/__init__.py
vss_cli/credentials/base.py
vss_cli/credentials/migration.py
vss_cli/credentials/backends/__init__.py
vss_cli/credentials/backends/encrypted.py
vss_cli/credentials/backends/keychain.py
vss_cli/credentials/backends/onepassword.py
vss_cli/data/clib.yaml
vss_cli/data/clone.yaml
vss_cli/data/config.yaml
vss_cli/data/image.yaml
vss_cli/data/shell.yaml
vss_cli/data/template.yaml
vss_cli/plugins/__init__.py
vss_cli/plugins/account.py
vss_cli/plugins/assist.py
vss_cli/plugins/completion.py
vss_cli/plugins/compute.py
vss_cli/plugins/configure.py
vss_cli/plugins/key.py
vss_cli/plugins/mcp.py
vss_cli/plugins/message.py
vss_cli/plugins/misc.py
vss_cli/plugins/ovf.py
vss_cli/plugins/plugins.py
vss_cli/plugins/raw.py
vss_cli/plugins/request.py
vss_cli/plugins/service.py
vss_cli/plugins/shell.py
vss_cli/plugins/status.py
vss_cli/plugins/stor.py
vss_cli/plugins/token.py
vss_cli/plugins/upgrade.py
vss_cli/plugins/vpn.py
vss_cli/plugins/compute_plugins/__init__.py
vss_cli/plugins/compute_plugins/callbacks.py
vss_cli/plugins/compute_plugins/contentlib.py
vss_cli/plugins/compute_plugins/domain.py
vss_cli/plugins/compute_plugins/floppy.py
vss_cli/plugins/compute_plugins/folder.py
vss_cli/plugins/compute_plugins/helper.py
vss_cli/plugins/compute_plugins/image.py
vss_cli/plugins/compute_plugins/inventory.py
vss_cli/plugins/compute_plugins/iso.py
vss_cli/plugins/compute_plugins/net.py
vss_cli/plugins/compute_plugins/os.py
vss_cli/plugins/compute_plugins/rel_args.py
vss_cli/plugins/compute_plugins/rel_opts.py
vss_cli/plugins/compute_plugins/template.py
vss_cli/plugins/compute_plugins/vm.py
vss_cli-2026.1.0.dist-info/licenses/LICENSE
vss_cli-2026.1.0.dist-info/METADATA
vss_cli-2026.1.0.dist-info/WHEEL
vss_cli-2026.1.0.dist-info/entry_points.txt
vss_cli-2026.1.0.dist-info/top_level.txt
vss_cli-2026.1.0.dist-info/RECORD
