Metadata-Version: 2.4
Name: vss-cli
Version: 2026.1.0
Summary: ITS Private Cloud CLI
Author-email: University of Toronto <vss-apps@eis.utoronto.ca>
Maintainer-email: vss-py@eis.utoronto.ca
License: MIT
Project-URL: Homepage, https://gitlab-ee.eis.utoronto.ca/vss/vss-cli
Project-URL: Documentation, https://eis.utoronto.ca/~vss/vss-cli/
Project-URL: Repository, https://gitlab-ee.eis.utoronto.ca/vss/vss-cli
Project-URL: Bug Reports, https://gitlab-ee.eis.utoronto.ca/vss/vss-cli/issues
Platform: any
Classifier: Development Status :: 5 - Production/Stable
Classifier: Intended Audience :: Developers
Classifier: License :: OSI Approved :: MIT License
Classifier: Programming Language :: Python :: 3.10
Classifier: Programming Language :: Python :: 3.11
Classifier: Programming Language :: Python :: 3.12
Classifier: Programming Language :: Python :: 3.13
Requires-Python: >=3.10
License-File: LICENSE
Requires-Dist: pyvss>=2025.2.1
Requires-Dist: click==8.1.8
Requires-Dist: click-log==0.4.0
Requires-Dist: click-plugins==1.1.1
Requires-Dist: click-repl==0.2.0
Requires-Dist: click-spinner==0.1.10
Requires-Dist: click-threading==0.5.0
Requires-Dist: tabulate==0.9.0
Requires-Dist: jsonpath-ng==1.7.0
Requires-Dist: jinja2>=2.10
Requires-Dist: dateparser==1.2.1
Requires-Dist: rich==13.9.4
Requires-Dist: pick==2.2.0
Requires-Dist: dataclasses-json==0.6.7
Requires-Dist: validators==0.34.0
Requires-Dist: ruamel.yaml==0.17.21
Requires-Dist: qrcode==7.3.1
Requires-Dist: pyjwt==2.6.0
Requires-Dist: xmltodict==0.13.0
Requires-Dist: keyring>=25.5.0
Requires-Dist: cryptography>=44.0.0
Provides-Extra: stor
Requires-Dist: minio==7.2.15; extra == "stor"
Provides-Extra: test
Requires-Dist: flake8==7.1.1; extra == "test"
Requires-Dist: nose==1.3.7; extra == "test"
Requires-Dist: coverage==7.6.12; extra == "test"
Requires-Dist: pytz==2025.1; extra == "test"
Requires-Dist: wheel==0.45.1; extra == "test"
Requires-Dist: minio==7.2.15; extra == "test"
Provides-Extra: dev
Requires-Dist: flake8==7.1.1; extra == "dev"
Requires-Dist: nose==1.3.7; extra == "dev"
Requires-Dist: coverage==7.6.12; extra == "dev"
Requires-Dist: pytz==2025.1; extra == "dev"
Requires-Dist: wheel==0.45.1; extra == "dev"
Requires-Dist: minio==7.2.15; extra == "dev"
Requires-Dist: sphinx-rtd-theme==1.3.0; extra == "dev"
Requires-Dist: Sphinx==7.2.2; extra == "dev"
Requires-Dist: bump2version==1.0.1; extra == "dev"
Requires-Dist: sphinxcontrib-jquery==4.1; extra == "dev"
Requires-Dist: sphinxcontrib-confluencebuilder==2.10.1; extra == "dev"
Provides-Extra: mcp
Requires-Dist: mcp-vss>=2025.6.1.dev5; extra == "mcp"
Requires-Dist: mcp[cli]>=1.7.1; extra == "mcp"
Dynamic: license-file
